{
  "listLeft" :[
                {
                    "url": "../../static/img/Hangout/1.jpg",
                    "isNew": "New",
                    "title": "多用途棕毛清洁刷",
                    "price": 9,
                    "oldPrice": "",
                    "comment": 11717
                },
                {
                    "url": "../../static/img/Hangout/2.jpg",
                    "isNew": "New",
                    "title": "洗头膏",
                    "price": 15,
                    "oldPrice": "",
                    "comment": 12345
                },
                {
                    "url": "../../static/img/Hangout/3.jpg",
                    "isNew": "New",
                    "title": "洗衣液",
                    "price": 18,
                    "oldPrice": "",
                    "comment": 2345
                },
                {
                    "url": "../../static/img/Hangout/4.jpg",
                    "isNew": "",
                    "title": "干果",
                    "price": 13,
                    "oldPrice": 17,
                    "comment": 1111
                },
                {
                    "url": "../../static/img/Hangout/5.jpg",
                    "isNew": "",
                    "title": "樱桃",
                    "price": 17,
                    "oldPrice": 20,
                    "comment": 12345
                },
                {
                    "url": "../../static/img/Hangout/1.jpg",
                    "isNew": "New",
                    "title": "多用途棕毛清洁刷",
                    "price": 9,
                    "oldPrice": "",
                    "comment": 11717
                },
                {
                    "url": "../../static/img/Hangout/2.jpg",
                    "isNew": "New",
                    "title": "洗头膏",
                    "price": 15,
                    "oldPrice": "",
                    "comment": 12345
                },
                {
                    "url": "../../static/img/Hangout/3.jpg",
                    "isNew": "New",
                    "title": "洗衣液",
                    "price": 18,
                    "oldPrice": "",
                    "comment": 2345
                },
                {
                    "url": "../../static/img/Hangout/4.jpg",
                    "isNew": "",
                    "title": "干果",
                    "price": 13,
                    "oldPrice": 17,
                    "comment": 1111
                },
                {
                    "url": "../../static/img/Hangout/5.jpg",
                    "isNew": "",
                    "title": "樱桃",
                    "price": 17,
                    "oldPrice": 20,
                    "comment": 12345
                },
                {
                    "url": "../../static/img/Hangout/1.jpg",
                    "isNew": "New",
                    "title": "多用途棕毛清洁刷",
                    "price": 9,
                    "oldPrice": "",
                    "comment": 11717
                },
                {
                    "url": "../../static/img/Hangout/2.jpg",
                    "isNew": "New",
                    "title": "洗头膏",
                    "price": 15,
                    "oldPrice": "",
                    "comment": 12345
                },
                {
                    "url": "../../static/img/Hangout/3.jpg",
                    "isNew": "New",
                    "title": "洗衣液",
                    "price": 18,
                    "oldPrice": "",
                    "comment": 2345
                },
                {
                    "url": "../../static/img/Hangout/4.jpg",
                    "isNew": "",
                    "title": "干果",
                    "price": 13,
                    "oldPrice": 17,
                    "comment": 1111
                },
                {
                    "url": "../../static/img/Hangout/5.jpg",
                    "isNew": "",
                    "title": "樱桃",
                    "price": 17,
                    "oldPrice": 20,
                    "comment": 12345
                }
      ]
}
